Metadata-Version: 2.1
Name: PyDirtyLineDetection
Version: 1.1
Summary: A toolset that is designed to be used to detect dirty borders in videos/images
Home-page: https://github.com/jlw4049/DirtyLineDetection
Author: Jessie Wilson
Author-email: jessielw4049@gmail.com
License: MIT
Keywords: PyDirtyLineDetection
Platform: UNKNOWN
Classifier: Development Status :: 5 - Production/Stable
Classifier: Intended Audience :: Developers
Classifier: Operating System :: Microsoft :: Windows
Classifier: Operating System :: MacOS
Classifier: Operating System :: POSIX :: Linux
Classifier: License :: OSI Approved :: MIT License
Classifier: Programming Language :: Python :: 3
License-File: LICENSE
